MuyGPyS/__init__.py
MuyGPyS/neighbors.py
MuyGPyS/_src/__init__.py
MuyGPyS/_src/config.py
MuyGPyS/_src/jaxconfig.py
MuyGPyS/_src/mpi_utils.py
MuyGPyS/_src/util.py
MuyGPyS/_src/gp/__init__.py
MuyGPyS/_src/gp/kernels/__init__.py
MuyGPyS/_src/gp/kernels/jax.py
MuyGPyS/_src/gp/kernels/mpi.py
MuyGPyS/_src/gp/kernels/numpy.py
MuyGPyS/_src/gp/kernels/torch.py
MuyGPyS/_src/gp/kernels/shear/__init__.py
MuyGPyS/_src/gp/kernels/shear/jax.py
MuyGPyS/_src/gp/kernels/shear/mpi.py
MuyGPyS/_src/gp/kernels/shear/numpy.py
MuyGPyS/_src/gp/kernels/shear/torch.py
MuyGPyS/_src/gp/kernels/soap/__init__.py
MuyGPyS/_src/gp/kernels/soap/jax.py
MuyGPyS/_src/gp/kernels/soap/mpi.py
MuyGPyS/_src/gp/kernels/soap/numpy.py
MuyGPyS/_src/gp/kernels/soap/torch.py
MuyGPyS/_src/gp/muygps/__init__.py
MuyGPyS/_src/gp/muygps/jax.py
MuyGPyS/_src/gp/muygps/mpi.py
MuyGPyS/_src/gp/muygps/numpy.py
MuyGPyS/_src/gp/muygps/torch.py
MuyGPyS/_src/gp/noise/__init__.py
MuyGPyS/_src/gp/noise/jax.py
MuyGPyS/_src/gp/noise/mpi.py
MuyGPyS/_src/gp/noise/numpy.py
MuyGPyS/_src/gp/noise/torch.py
MuyGPyS/_src/gp/tensors/__init__.py
MuyGPyS/_src/gp/tensors/jax.py
MuyGPyS/_src/gp/tensors/mpi.py
MuyGPyS/_src/gp/tensors/numpy.py
MuyGPyS/_src/gp/tensors/torch.py
MuyGPyS/_src/math/__init__.py
MuyGPyS/_src/math/jax.py
MuyGPyS/_src/math/meta.py
MuyGPyS/_src/math/mpi.py
MuyGPyS/_src/math/numpy.py
MuyGPyS/_src/math/torch.py
MuyGPyS/_src/optimize/__init__.py
MuyGPyS/_src/optimize/chassis/__init__.py
MuyGPyS/_src/optimize/chassis/jax.py
MuyGPyS/_src/optimize/chassis/mpi.py
MuyGPyS/_src/optimize/chassis/numpy.py
MuyGPyS/_src/optimize/chassis/torch.py
MuyGPyS/_src/optimize/loss/__init__.py
MuyGPyS/_src/optimize/loss/jax.py
MuyGPyS/_src/optimize/loss/mpi.py
MuyGPyS/_src/optimize/loss/numpy.py
MuyGPyS/_src/optimize/loss/torch.py
MuyGPyS/_src/optimize/scale/__init__.py
MuyGPyS/_src/optimize/scale/jax.py
MuyGPyS/_src/optimize/scale/mpi.py
MuyGPyS/_src/optimize/scale/numpy.py
MuyGPyS/_src/optimize/scale/torch.py
MuyGPyS/_test/__init__.py
muygpys-0.9.1.dist-info/licenses/LICENSE-MIT
muygpys-0.9.1.dist-info/licenses/NOTICE
muygpys-0.9.1.dist-info/METADATA
muygpys-0.9.1.dist-info/WHEEL
muygpys-0.9.1.dist-info/top_level.txt
muygpys-0.9.1.dist-info/RECORD
