Metadata-Version: 2.4
Name: muygpys
Version: 0.9.1
Summary: Scalable Approximate Gaussian Process using Sparse Kriging
Author: Min W. Priest
License: MIT License
Project-URL: homepage, https://github.com/LLNL/MuyGPyS
Project-URL: source, https://github.com/LLNL/MuyGPyS
Project-URL: download, https://pypi.org/project/muygpys
Project-URL: documentation, https://muygpys.readthedocs.io
Project-URL: tracker, https://github.com/LLNL/MuyGPyS/issues
Classifier: Programming Language :: Python :: 3.8
Classifier: Programming Language :: Python :: 3.9
Classifier: Programming Language :: Python :: 3.10
Classifier: Programming Language :: Python :: 3.11
Classifier: Programming Language :: Python :: 3.12
Classifier: License :: OSI Approved :: MIT License
Classifier: Operating System :: MacOS
Classifier: Operating System :: POSIX :: Linux
Classifier: Topic :: Software Development
Classifier: Topic :: Software Development :: Libraries
Classifier: Topic :: Software Development :: Libraries :: Python Modules
Classifier: Topic :: Scientific/Engineering
Classifier: Topic :: Scientific/Engineering :: Mathematics
Classifier: Intended Audience :: Science/Research
Classifier: Intended Audience :: Developers
Classifier: Intended Audience :: Education
Classifier: Development Status :: 3 - Alpha
Requires-Python: >=3.8
License-File: LICENSE-MIT
License-File: NOTICE
Requires-Dist: numpy>=1.18.5
Requires-Dist: scipy>=1.9.0
Requires-Dist: scikit-learn>=0.23.2
Requires-Dist: bayesian-optimization>=1.4.2
Provides-Extra: tests
Requires-Dist: absl-py>=0.13.0; extra == "tests"
Requires-Dist: matplotlib>=3.2.1; extra == "tests"
Requires-Dist: pandas>=2.2.2; extra == "tests"
Requires-Dist: flake8; extra == "tests"
Provides-Extra: dev
Requires-Dist: black>=21.1.0; extra == "dev"
Requires-Dist: build>=0.7.0; extra == "dev"
Requires-Dist: mypy>=0.910; extra == "dev"
Requires-Dist: twine>=3.7.1; extra == "dev"
Requires-Dist: h5py>=3.7.0; extra == "dev"
Provides-Extra: docs
Requires-Dist: sphinx==6.2.1; extra == "docs"
Requires-Dist: sphinx-rtd-theme==1.2.2; extra == "docs"
Requires-Dist: sphinx-autodoc-typehints==1.22; extra == "docs"
Requires-Dist: matplotlib>=3.2.1; extra == "docs"
Requires-Dist: nbsphinx==0.9.2; extra == "docs"
Requires-Dist: pandas>=2.2.2; extra == "docs"
Requires-Dist: pandoc==2.3.0; extra == "docs"
Requires-Dist: pandocfilters==1.5.0; extra == "docs"
Requires-Dist: ipython==7.30.1; extra == "docs"
Requires-Dist: ipykernel==6.6.0; extra == "docs"
Requires-Dist: torchvision>=0.14.1; extra == "docs"
Requires-Dist: cblind>=2.3.1; extra == "docs"
Provides-Extra: hnswlib
Requires-Dist: pybind11>=2.5.0; extra == "hnswlib"
Requires-Dist: hnswlib>=0.6.0; extra == "hnswlib"
Provides-Extra: jax
Requires-Dist: jax>=0.4.0; extra == "jax"
Requires-Dist: tensorflow-probability[jax]>=0.25.0; extra == "jax"
Provides-Extra: mpi
Requires-Dist: mpi4py==3.1.3; extra == "mpi"
Provides-Extra: torch
Requires-Dist: torch>=1.13.0; extra == "torch"
Requires-Dist: torchvision>=0.14.1; extra == "torch"
Dynamic: license-file
